Kpickmenu.cp312-win_amd64.pyd
Kpickmenu-1.0.dist-info/METADATA
Kpickmenu-1.0.dist-info/WHEEL
Kpickmenu-1.0.dist-info/top_level.txt
Kpickmenu-1.0.dist-info/RECORD
