Metadata-Version: 2.1
Name: Kpickmenu
Version: 1.0
Summary: Python module for creating menus
Home-page: https://github.com/krendel001/Kpick
Author: krendel
Author-email: 39krendeloff39@gmail.com
Classifier: Programming Language :: Python :: 3
Classifier: License :: OSI Approved :: MIT License
Classifier: Operating System :: OS Independent
Requires-Python: >=3.6
